{
  "updatedAt": "2026-05-10T14:21:45.049Z",
  "routes": [
    {
      "id": 1,
      "name": "古平岗→新庄",
      "start": "古平岗站",
      "end": "新庄站",
      "points": [
        {
          "latitude": 32.071279,
          "longitude": 118.757972
        },
        {
          "latitude": 32.071237,
          "longitude": 118.75748
        },
        {
          "latitude": 32.07106,
          "longitude": 118.755968
        },
        {
          "latitude": 32.071135,
          "longitude": 118.755656
        },
        {
          "latitude": 32.071189,
          "longitude": 118.755533
        },
        {
          "latitude": 32.071237,
          "longitude": 118.755463
        },
        {
          "latitude": 32.071317,
          "longitude": 118.755383
        },
        {
          "latitude": 32.071419,
          "longitude": 118.755313
        },
        {
          "latitude": 32.071591,
          "longitude": 118.75526
        },
        {
          "latitude": 32.071779,
          "longitude": 118.75527
        },
        {
          "latitude": 32.071908,
          "longitude": 118.755318
        },
        {
          "latitude": 32.072047,
          "longitude": 118.75542
        },
        {
          "latitude": 32.072143,
          "longitude": 118.755565
        },
        {
          "latitude": 32.072181,
          "longitude": 118.755678
        },
        {
          "latitude": 32.072192,
          "longitude": 118.755775
        },
        {
          "latitude": 32.072186,
          "longitude": 118.755919
        },
        {
          "latitude": 32.072095,
          "longitude": 118.756311
        },
        {
          "latitude": 32.072079,
          "longitude": 118.756402
        },
        {
          "latitude": 32.071763,
          "longitude": 118.756815
        },
        {
          "latitude": 32.071586,
          "longitude": 118.756981
        },
        {
          "latitude": 32.071435,
          "longitude": 118.757094
        },
        {
          "latitude": 32.071242,
          "longitude": 118.757212
        },
        {
          "latitude": 32.07106,
          "longitude": 118.757303
        },
        {
          "latitude": 32.070867,
          "longitude": 118.757378
        },
        {
          "latitude": 32.070663,
          "longitude": 118.757427
        },
        {
          "latitude": 32.070438,
          "longitude": 118.757459
        },
        {
          "latitude": 32.070175,
          "longitude": 118.757475
        },
        {
          "latitude": 32.069858,
          "longitude": 118.75747
        },
        {
          "latitude": 32.069391,
          "longitude": 118.757438
        },
        {
          "latitude": 32.069091,
          "longitude": 118.757395
        },
        {
          "latitude": 32.068936,
          "longitude": 118.757373
        },
        {
          "latitude": 32.068598,
          "longitude": 118.757303
        },
        {
          "latitude": 32.068265,
          "longitude": 118.757207
        },
        {
          "latitude": 32.066377,
          "longitude": 118.756541
        },
        {
          "latitude": 32.065931,
          "longitude": 118.756408
        },
        {
          "latitude": 32.065889,
          "longitude": 118.756391
        },
        {
          "latitude": 32.065851,
          "longitude": 118.756375
        },
        {
          "latitude": 32.065636,
          "longitude": 118.75629
        },
        {
          "latitude": 32.065433,
          "longitude": 118.756209
        },
        {
          "latitude": 32.065014,
          "longitude": 118.756091
        },
        {
          "latitude": 32.06488,
          "longitude": 118.756005
        },
        {
          "latitude": 32.064789,
          "longitude": 118.755957
        },
        {
          "latitude": 32.064456,
          "longitude": 118.755871
        },
        {
          "latitude": 32.064091,
          "longitude": 118.755807
        },
        {
          "latitude": 32.063636,
          "longitude": 118.755764
        },
        {
          "latitude": 32.062895,
          "longitude": 118.75571
        },
        {
          "latitude": 32.062117,
          "longitude": 118.755678
        },
        {
          "latitude": 32.06201,
          "longitude": 118.755678
        },
        {
          "latitude": 32.061919,
          "longitude": 118.755753
        },
        {
          "latitude": 32.061892,
          "longitude": 118.755855
        },
        {
          "latitude": 32.061908,
          "longitude": 118.755935
        },
        {
          "latitude": 32.061994,
          "longitude": 118.756026
        },
        {
          "latitude": 32.062246,
          "longitude": 118.756026
        },
        {
          "latitude": 32.06281,
          "longitude": 118.756064
        },
        {
          "latitude": 32.063255,
          "longitude": 118.75608
        },
        {
          "latitude": 32.063571,
          "longitude": 118.756091
        },
        {
          "latitude": 32.06378,
          "longitude": 118.756107
        },
        {
          "latitude": 32.064258,
          "longitude": 118.756182
        },
        {
          "latitude": 32.064585,
          "longitude": 118.756236
        },
        {
          "latitude": 32.064966,
          "longitude": 118.756225
        },
        {
          "latitude": 32.065181,
          "longitude": 118.756279
        },
        {
          "latitude": 32.065486,
          "longitude": 118.756365
        },
        {
          "latitude": 32.066398,
          "longitude": 118.75666
        },
        {
          "latitude": 32.067906,
          "longitude": 118.75718
        },
        {
          "latitude": 32.068351,
          "longitude": 118.757336
        },
        {
          "latitude": 32.068694,
          "longitude": 118.757427
        },
        {
          "latitude": 32.069091,
          "longitude": 118.757496
        },
        {
          "latitude": 32.069145,
          "longitude": 118.757507
        },
        {
          "latitude": 32.069456,
          "longitude": 118.757545
        },
        {
          "latitude": 32.069606,
          "longitude": 118.757609
        },
        {
          "latitude": 32.069692,
          "longitude": 118.757641
        },
        {
          "latitude": 32.069869,
          "longitude": 118.757668
        },
        {
          "latitude": 32.070132,
          "longitude": 118.757684
        },
        {
          "latitude": 32.070604,
          "longitude": 118.757684
        },
        {
          "latitude": 32.070706,
          "longitude": 118.757695
        },
        {
          "latitude": 32.070802,
          "longitude": 118.757716
        },
        {
          "latitude": 32.070883,
          "longitude": 118.757749
        },
        {
          "latitude": 32.070936,
          "longitude": 118.757791
        },
        {
          "latitude": 32.071044,
          "longitude": 118.757904
        },
        {
          "latitude": 32.071098,
          "longitude": 118.758017
        },
        {
          "latitude": 32.071183,
          "longitude": 118.758248
        },
        {
          "latitude": 32.071221,
          "longitude": 118.758843
        },
        {
          "latitude": 32.071231,
          "longitude": 118.759535
        },
        {
          "latitude": 32.071221,
          "longitude": 118.760329
        },
        {
          "latitude": 32.071215,
          "longitude": 118.760479
        },
        {
          "latitude": 32.071215,
          "longitude": 118.760817
        },
        {
          "latitude": 32.071226,
          "longitude": 118.761101
        },
        {
          "latitude": 32.071258,
          "longitude": 118.761364
        },
        {
          "latitude": 32.071307,
          "longitude": 118.761713
        },
        {
          "latitude": 32.071425,
          "longitude": 118.762206
        },
        {
          "latitude": 32.071484,
          "longitude": 118.762426
        },
        {
          "latitude": 32.071709,
          "longitude": 118.763027
        },
        {
          "latitude": 32.071886,
          "longitude": 118.763381
        },
        {
          "latitude": 32.071988,
          "longitude": 118.763569
        },
        {
          "latitude": 32.072181,
          "longitude": 118.76387
        },
        {
          "latitude": 32.072556,
          "longitude": 118.764347
        },
        {
          "latitude": 32.074815,
          "longitude": 118.767018
        },
        {
          "latitude": 32.076194,
          "longitude": 118.768676
        },
        {
          "latitude": 32.07658,
          "longitude": 118.769148
        },
        {
          "latitude": 32.076778,
          "longitude": 118.769416
        },
        {
          "latitude": 32.076945,
          "longitude": 118.769722
        },
        {
          "latitude": 32.077095,
          "longitude": 118.770076
        },
        {
          "latitude": 32.077202,
          "longitude": 118.770441
        },
        {
          "latitude": 32.077234,
          "longitude": 118.770623
        },
        {
          "latitude": 32.077272,
          "longitude": 118.770859
        },
        {
          "latitude": 32.077299,
          "longitude": 118.771229
        },
        {
          "latitude": 32.07732,
          "longitude": 118.772468
        },
        {
          "latitude": 32.077331,
          "longitude": 118.773118
        },
        {
          "latitude": 32.077352,
          "longitude": 118.775242
        },
        {
          "latitude": 32.077358,
          "longitude": 118.775703
        },
        {
          "latitude": 32.077363,
          "longitude": 118.776288
        },
        {
          "latitude": 32.077368,
          "longitude": 118.776449
        },
        {
          "latitude": 32.077368,
          "longitude": 118.776653
        },
        {
          "latitude": 32.077379,
          "longitude": 118.777221
        },
        {
          "latitude": 32.077374,
          "longitude": 118.777817
        },
        {
          "latitude": 32.07739,
          "longitude": 118.778278
        },
        {
          "latitude": 32.077433,
          "longitude": 118.779104
        },
        {
          "latitude": 32.077444,
          "longitude": 118.779786
        },
        {
          "latitude": 32.07746,
          "longitude": 118.780789
        },
        {
          "latitude": 32.077508,
          "longitude": 118.783932
        },
        {
          "latitude": 32.077497,
          "longitude": 118.784061
        },
        {
          "latitude": 32.077497,
          "longitude": 118.784179
        },
        {
          "latitude": 32.077535,
          "longitude": 118.785799
        },
        {
          "latitude": 32.07761,
          "longitude": 118.7867
        },
        {
          "latitude": 32.077685,
          "longitude": 118.787199
        },
        {
          "latitude": 32.077814,
          "longitude": 118.787875
        },
        {
          "latitude": 32.078141,
          "longitude": 118.789125
        },
        {
          "latitude": 32.078699,
          "longitude": 118.791169
        },
        {
          "latitude": 32.078817,
          "longitude": 118.791641
        },
        {
          "latitude": 32.078913,
          "longitude": 118.79214
        },
        {
          "latitude": 32.078967,
          "longitude": 118.79258
        },
        {
          "latitude": 32.079005,
          "longitude": 118.793068
        },
        {
          "latitude": 32.078999,
          "longitude": 118.793578
        },
        {
          "latitude": 32.078967,
          "longitude": 118.79406
        },
        {
          "latitude": 32.078887,
          "longitude": 118.794581
        },
        {
          "latitude": 32.078747,
          "longitude": 118.795235
        },
        {
          "latitude": 32.076693,
          "longitude": 118.803255
        },
        {
          "latitude": 32.07651,
          "longitude": 118.803931
        },
        {
          "latitude": 32.076398,
          "longitude": 118.804323
        },
        {
          "latitude": 32.076322,
          "longitude": 118.804778
        },
        {
          "latitude": 32.07629,
          "longitude": 118.805047
        },
        {
          "latitude": 32.076247,
          "longitude": 118.805154
        },
        {
          "latitude": 32.076226,
          "longitude": 118.805277
        },
        {
          "latitude": 32.076194,
          "longitude": 118.805701
        },
        {
          "latitude": 32.07621,
          "longitude": 118.80612
        },
        {
          "latitude": 32.076215,
          "longitude": 118.806152
        },
        {
          "latitude": 32.076242,
          "longitude": 118.806388
        },
        {
          "latitude": 32.076301,
          "longitude": 118.806704
        },
        {
          "latitude": 32.076408,
          "longitude": 118.807096
        },
        {
          "latitude": 32.076494,
          "longitude": 118.807364
        },
        {
          "latitude": 32.076542,
          "longitude": 118.807536
        },
        {
          "latitude": 32.076693,
          "longitude": 118.807906
        },
        {
          "latitude": 32.076929,
          "longitude": 118.808475
        },
        {
          "latitude": 32.077009,
          "longitude": 118.808721
        },
        {
          "latitude": 32.077143,
          "longitude": 118.808979
        },
        {
          "latitude": 32.077106,
          "longitude": 118.809048
        },
        {
          "latitude": 32.077073,
          "longitude": 118.809129
        },
        {
          "latitude": 32.077057,
          "longitude": 118.809188
        },
        {
          "latitude": 32.077052,
          "longitude": 118.809279
        },
        {
          "latitude": 32.077057,
          "longitude": 118.809365
        },
        {
          "latitude": 32.077073,
          "longitude": 118.809456
        },
        {
          "latitude": 32.077111,
          "longitude": 118.809574
        },
        {
          "latitude": 32.077154,
          "longitude": 118.80966
        },
        {
          "latitude": 32.077229,
          "longitude": 118.809757
        },
        {
          "latitude": 32.077299,
          "longitude": 118.809826
        },
        {
          "latitude": 32.077385,
          "longitude": 118.809875
        },
        {
          "latitude": 32.077454,
          "longitude": 118.809901
        },
        {
          "latitude": 32.07753,
          "longitude": 118.809912
        },
        {
          "latitude": 32.077599,
          "longitude": 118.809918
        },
        {
          "latitude": 32.07768,
          "longitude": 118.809907
        },
        {
          "latitude": 32.07776,
          "longitude": 118.809885
        },
        {
          "latitude": 32.077825,
          "longitude": 118.809864
        },
        {
          "latitude": 32.077916,
          "longitude": 118.809805
        },
        {
          "latitude": 32.07857,
          "longitude": 118.810411
        },
        {
          "latitude": 32.079241,
          "longitude": 118.810996
        },
        {
          "latitude": 32.079621,
          "longitude": 118.811328
        },
        {
          "latitude": 32.079514,
          "longitude": 118.811366
        },
        {
          "latitude": 32.079412,
          "longitude": 118.811403
        },
        {
          "latitude": 32.079284,
          "longitude": 118.811452
        },
        {
          "latitude": 32.079155,
          "longitude": 118.811489
        },
        {
          "latitude": 32.079064,
          "longitude": 118.811259
        },
        {
          "latitude": 32.078763,
          "longitude": 118.810942
        },
        {
          "latitude": 32.078677,
          "longitude": 118.810851
        },
        {
          "latitude": 32.078506,
          "longitude": 118.810722
        },
        {
          "latitude": 32.078345,
          "longitude": 118.810599
        },
        {
          "latitude": 32.078023,
          "longitude": 118.810438
        },
        {
          "latitude": 32.077926,
          "longitude": 118.810432
        },
        {
          "latitude": 32.077642,
          "longitude": 118.810524
        },
        {
          "latitude": 32.07747,
          "longitude": 118.8104
        },
        {
          "latitude": 32.077438,
          "longitude": 118.810395
        },
        {
          "latitude": 32.07688,
          "longitude": 118.810535
        }
      ]
    },
    {
      "id": 2,
      "name": "草场门→九华山",
      "start": "草场门站",
      "end": "九华山站",
      "points": [
        {
          "latitude": 32.060425,
          "longitude": 118.755939
        },
        {
          "latitude": 32.060471,
          "longitude": 118.755935
        },
        {
          "latitude": 32.060573,
          "longitude": 118.755941
        },
        {
          "latitude": 32.061077,
          "longitude": 118.755946
        },
        {
          "latitude": 32.061656,
          "longitude": 118.755935
        },
        {
          "latitude": 32.061796,
          "longitude": 118.755957
        },
        {
          "latitude": 32.061994,
          "longitude": 118.756026
        },
        {
          "latitude": 32.062246,
          "longitude": 118.756026
        },
        {
          "latitude": 32.06281,
          "longitude": 118.756064
        },
        {
          "latitude": 32.063255,
          "longitude": 118.75608
        },
        {
          "latitude": 32.063571,
          "longitude": 118.756091
        },
        {
          "latitude": 32.06378,
          "longitude": 118.756107
        },
        {
          "latitude": 32.064258,
          "longitude": 118.756182
        },
        {
          "latitude": 32.064585,
          "longitude": 118.756236
        },
        {
          "latitude": 32.064966,
          "longitude": 118.756225
        },
        {
          "latitude": 32.065181,
          "longitude": 118.756279
        },
        {
          "latitude": 32.065486,
          "longitude": 118.756365
        },
        {
          "latitude": 32.066398,
          "longitude": 118.75666
        },
        {
          "latitude": 32.067906,
          "longitude": 118.75718
        },
        {
          "latitude": 32.068351,
          "longitude": 118.757336
        },
        {
          "latitude": 32.068694,
          "longitude": 118.757427
        },
        {
          "latitude": 32.069091,
          "longitude": 118.757496
        },
        {
          "latitude": 32.069145,
          "longitude": 118.757507
        },
        {
          "latitude": 32.069456,
          "longitude": 118.757545
        },
        {
          "latitude": 32.069606,
          "longitude": 118.757609
        },
        {
          "latitude": 32.069692,
          "longitude": 118.757641
        },
        {
          "latitude": 32.069869,
          "longitude": 118.757668
        },
        {
          "latitude": 32.070132,
          "longitude": 118.757684
        },
        {
          "latitude": 32.070604,
          "longitude": 118.757684
        },
        {
          "latitude": 32.070706,
          "longitude": 118.757695
        },
        {
          "latitude": 32.070802,
          "longitude": 118.757716
        },
        {
          "latitude": 32.070883,
          "longitude": 118.757749
        },
        {
          "latitude": 32.070936,
          "longitude": 118.757791
        },
        {
          "latitude": 32.071044,
          "longitude": 118.757904
        },
        {
          "latitude": 32.071098,
          "longitude": 118.758017
        },
        {
          "latitude": 32.071183,
          "longitude": 118.758248
        },
        {
          "latitude": 32.071221,
          "longitude": 118.758843
        },
        {
          "latitude": 32.071231,
          "longitude": 118.759535
        },
        {
          "latitude": 32.071221,
          "longitude": 118.760329
        },
        {
          "latitude": 32.071215,
          "longitude": 118.760479
        },
        {
          "latitude": 32.071215,
          "longitude": 118.760817
        },
        {
          "latitude": 32.071226,
          "longitude": 118.761101
        },
        {
          "latitude": 32.071258,
          "longitude": 118.761364
        },
        {
          "latitude": 32.071307,
          "longitude": 118.761713
        },
        {
          "latitude": 32.071425,
          "longitude": 118.762206
        },
        {
          "latitude": 32.071484,
          "longitude": 118.762426
        },
        {
          "latitude": 32.071709,
          "longitude": 118.763027
        },
        {
          "latitude": 32.071886,
          "longitude": 118.763381
        },
        {
          "latitude": 32.071988,
          "longitude": 118.763569
        },
        {
          "latitude": 32.072181,
          "longitude": 118.76387
        },
        {
          "latitude": 32.072556,
          "longitude": 118.764347
        },
        {
          "latitude": 32.074815,
          "longitude": 118.767018
        },
        {
          "latitude": 32.076194,
          "longitude": 118.768676
        },
        {
          "latitude": 32.07658,
          "longitude": 118.769148
        },
        {
          "latitude": 32.076778,
          "longitude": 118.769416
        },
        {
          "latitude": 32.076945,
          "longitude": 118.769722
        },
        {
          "latitude": 32.077095,
          "longitude": 118.770076
        },
        {
          "latitude": 32.077202,
          "longitude": 118.770441
        },
        {
          "latitude": 32.077234,
          "longitude": 118.770623
        },
        {
          "latitude": 32.077272,
          "longitude": 118.770859
        },
        {
          "latitude": 32.077299,
          "longitude": 118.771229
        },
        {
          "latitude": 32.07732,
          "longitude": 118.772468
        },
        {
          "latitude": 32.077331,
          "longitude": 118.773118
        },
        {
          "latitude": 32.077352,
          "longitude": 118.775242
        },
        {
          "latitude": 32.077358,
          "longitude": 118.775703
        },
        {
          "latitude": 32.077363,
          "longitude": 118.776288
        },
        {
          "latitude": 32.077368,
          "longitude": 118.776449
        },
        {
          "latitude": 32.077368,
          "longitude": 118.776653
        },
        {
          "latitude": 32.077379,
          "longitude": 118.777221
        },
        {
          "latitude": 32.077374,
          "longitude": 118.777817
        },
        {
          "latitude": 32.07739,
          "longitude": 118.778278
        },
        {
          "latitude": 32.077433,
          "longitude": 118.779104
        },
        {
          "latitude": 32.077444,
          "longitude": 118.779786
        },
        {
          "latitude": 32.07746,
          "longitude": 118.780789
        },
        {
          "latitude": 32.077508,
          "longitude": 118.783932
        },
        {
          "latitude": 32.077497,
          "longitude": 118.784061
        },
        {
          "latitude": 32.077497,
          "longitude": 118.784179
        },
        {
          "latitude": 32.077535,
          "longitude": 118.785799
        },
        {
          "latitude": 32.07761,
          "longitude": 118.7867
        },
        {
          "latitude": 32.077685,
          "longitude": 118.787199
        },
        {
          "latitude": 32.077814,
          "longitude": 118.787875
        },
        {
          "latitude": 32.078141,
          "longitude": 118.789125
        },
        {
          "latitude": 32.078699,
          "longitude": 118.791169
        },
        {
          "latitude": 32.078817,
          "longitude": 118.791641
        },
        {
          "latitude": 32.078913,
          "longitude": 118.79214
        },
        {
          "latitude": 32.078967,
          "longitude": 118.79258
        },
        {
          "latitude": 32.079005,
          "longitude": 118.793068
        },
        {
          "latitude": 32.078999,
          "longitude": 118.793578
        },
        {
          "latitude": 32.078967,
          "longitude": 118.79406
        },
        {
          "latitude": 32.078887,
          "longitude": 118.794581
        },
        {
          "latitude": 32.078747,
          "longitude": 118.795235
        },
        {
          "latitude": 32.076693,
          "longitude": 118.803255
        },
        {
          "latitude": 32.07651,
          "longitude": 118.803931
        },
        {
          "latitude": 32.076215,
          "longitude": 118.804237
        },
        {
          "latitude": 32.07614,
          "longitude": 118.804301
        },
        {
          "latitude": 32.07607,
          "longitude": 118.804344
        },
        {
          "latitude": 32.075936,
          "longitude": 118.804408
        },
        {
          "latitude": 32.075748,
          "longitude": 118.804451
        },
        {
          "latitude": 32.075502,
          "longitude": 118.804467
        },
        {
          "latitude": 32.075003,
          "longitude": 118.804451
        },
        {
          "latitude": 32.074354,
          "longitude": 118.804483
        },
        {
          "latitude": 32.073801,
          "longitude": 118.804591
        },
        {
          "latitude": 32.073678,
          "longitude": 118.804639
        },
        {
          "latitude": 32.073506,
          "longitude": 118.804746
        },
        {
          "latitude": 32.072878,
          "longitude": 118.804907
        },
        {
          "latitude": 32.07216,
          "longitude": 118.805213
        },
        {
          "latitude": 32.071248,
          "longitude": 118.805712
        },
        {
          "latitude": 32.07047,
          "longitude": 118.806152
        },
        {
          "latitude": 32.069091,
          "longitude": 118.80693
        },
        {
          "latitude": 32.067611,
          "longitude": 118.807772
        },
        {
          "latitude": 32.066886,
          "longitude": 118.808158
        },
        {
          "latitude": 32.06635,
          "longitude": 118.808389
        },
        {
          "latitude": 32.06598,
          "longitude": 118.808528
        },
        {
          "latitude": 32.065647,
          "longitude": 118.808635
        },
        {
          "latitude": 32.065277,
          "longitude": 118.808721
        },
        {
          "latitude": 32.064896,
          "longitude": 118.808802
        },
        {
          "latitude": 32.064521,
          "longitude": 118.808866
        },
        {
          "latitude": 32.064118,
          "longitude": 118.808904
        },
        {
          "latitude": 32.0637,
          "longitude": 118.808931
        },
        {
          "latitude": 32.062868,
          "longitude": 118.808904
        },
        {
          "latitude": 32.058105,
          "longitude": 118.808335
        },
        {
          "latitude": 32.057547,
          "longitude": 118.808271
        },
        {
          "latitude": 32.05627,
          "longitude": 118.808131
        },
        {
          "latitude": 32.054387,
          "longitude": 118.807911
        },
        {
          "latitude": 32.054366,
          "longitude": 118.807906
        },
        {
          "latitude": 32.05421,
          "longitude": 118.80789
        },
        {
          "latitude": 32.053851,
          "longitude": 118.807852
        },
        {
          "latitude": 32.053658,
          "longitude": 118.807831
        },
        {
          "latitude": 32.05354,
          "longitude": 118.807804
        },
        {
          "latitude": 32.053508,
          "longitude": 118.807788
        },
        {
          "latitude": 32.053315,
          "longitude": 118.807681
        },
        {
          "latitude": 32.052912,
          "longitude": 118.807605
        },
        {
          "latitude": 32.052676,
          "longitude": 118.807573
        },
        {
          "latitude": 32.052649,
          "longitude": 118.807568
        },
        {
          "latitude": 32.051394,
          "longitude": 118.807391
        },
        {
          "latitude": 32.051362,
          "longitude": 118.807723
        },
        {
          "latitude": 32.051619,
          "longitude": 118.807788
        },
        {
          "latitude": 32.051914,
          "longitude": 118.807847
        },
        {
          "latitude": 32.052461,
          "longitude": 118.807943
        },
        {
          "latitude": 32.053223,
          "longitude": 118.808013
        },
        {
          "latitude": 32.053298,
          "longitude": 118.808013
        },
        {
          "latitude": 32.053422,
          "longitude": 118.808008
        },
        {
          "latitude": 32.053556,
          "longitude": 118.807954
        },
        {
          "latitude": 32.053786,
          "longitude": 118.807976
        },
        {
          "latitude": 32.0542,
          "longitude": 118.808024
        },
        {
          "latitude": 32.054339,
          "longitude": 118.808045
        },
        {
          "latitude": 32.05442,
          "longitude": 118.80811
        },
        {
          "latitude": 32.054521,
          "longitude": 118.808174
        },
        {
          "latitude": 32.054881,
          "longitude": 118.808238
        },
        {
          "latitude": 32.056007,
          "longitude": 118.808378
        },
        {
          "latitude": 32.056474,
          "longitude": 118.80841
        },
        {
          "latitude": 32.056533,
          "longitude": 118.80841
        },
        {
          "latitude": 32.056726,
          "longitude": 118.808416
        },
        {
          "latitude": 32.057279,
          "longitude": 118.808475
        },
        {
          "latitude": 32.057413,
          "longitude": 118.808174
        },
        {
          "latitude": 32.057343,
          "longitude": 118.807707
        },
        {
          "latitude": 32.057273,
          "longitude": 118.807187
        },
        {
          "latitude": 32.05729,
          "longitude": 118.806667
        },
        {
          "latitude": 32.057365,
          "longitude": 118.806152
        },
        {
          "latitude": 32.057386,
          "longitude": 118.805991
        },
        {
          "latitude": 32.057401,
          "longitude": 118.80587
        }
      ]
    },
    {
      "id": 3,
      "name": "汉中门→西安门",
      "start": "汉中门站",
      "end": "西安门站",
      "points": [
        {
          "latitude": 32.042851,
          "longitude": 118.767115
        },
        {
          "latitude": 32.042816,
          "longitude": 118.766949
        },
        {
          "latitude": 32.0428,
          "longitude": 118.766879
        },
        {
          "latitude": 32.042746,
          "longitude": 118.766729
        },
        {
          "latitude": 32.042612,
          "longitude": 118.766428
        },
        {
          "latitude": 32.042446,
          "longitude": 118.766144
        },
        {
          "latitude": 32.042398,
          "longitude": 118.766063
        },
        {
          "latitude": 32.042312,
          "longitude": 118.766123
        },
        {
          "latitude": 32.042393,
          "longitude": 118.766273
        },
        {
          "latitude": 32.042537,
          "longitude": 118.76652
        },
        {
          "latitude": 32.042634,
          "longitude": 118.76675
        },
        {
          "latitude": 32.042688,
          "longitude": 118.766873
        },
        {
          "latitude": 32.042779,
          "longitude": 118.767142
        },
        {
          "latitude": 32.042827,
          "longitude": 118.767346
        },
        {
          "latitude": 32.042843,
          "longitude": 118.767528
        },
        {
          "latitude": 32.042843,
          "longitude": 118.767796
        },
        {
          "latitude": 32.042806,
          "longitude": 118.768236
        },
        {
          "latitude": 32.042763,
          "longitude": 118.768939
        },
        {
          "latitude": 32.042763,
          "longitude": 118.768976
        },
        {
          "latitude": 32.042618,
          "longitude": 118.770934
        },
        {
          "latitude": 32.04258,
          "longitude": 118.771637
        },
        {
          "latitude": 32.042575,
          "longitude": 118.771696
        },
        {
          "latitude": 32.042495,
          "longitude": 118.772806
        },
        {
          "latitude": 32.042425,
          "longitude": 118.774078
        },
        {
          "latitude": 32.042382,
          "longitude": 118.774845
        },
        {
          "latitude": 32.042328,
          "longitude": 118.775537
        },
        {
          "latitude": 32.042269,
          "longitude": 118.776186
        },
        {
          "latitude": 32.042264,
          "longitude": 118.776266
        },
        {
          "latitude": 32.042173,
          "longitude": 118.777458
        },
        {
          "latitude": 32.042119,
          "longitude": 118.77838
        },
        {
          "latitude": 32.042113,
          "longitude": 118.778471
        },
        {
          "latitude": 32.042092,
          "longitude": 118.778783
        },
        {
          "latitude": 32.042071,
          "longitude": 118.779056
        },
        {
          "latitude": 32.042044,
          "longitude": 118.779469
        },
        {
          "latitude": 32.042022,
          "longitude": 118.779695
        },
        {
          "latitude": 32.041904,
          "longitude": 118.78139
        },
        {
          "latitude": 32.041835,
          "longitude": 118.782511
        },
        {
          "latitude": 32.041829,
          "longitude": 118.782634
        },
        {
          "latitude": 32.041802,
          "longitude": 118.78294
        },
        {
          "latitude": 32.041711,
          "longitude": 118.784029
        },
        {
          "latitude": 32.0417,
          "longitude": 118.784163
        },
        {
          "latitude": 32.0417,
          "longitude": 118.784179
        },
        {
          "latitude": 32.041658,
          "longitude": 118.784844
        },
        {
          "latitude": 32.041652,
          "longitude": 118.78493
        },
        {
          "latitude": 32.041577,
          "longitude": 118.78596
        },
        {
          "latitude": 32.04155,
          "longitude": 118.786175
        },
        {
          "latitude": 32.04154,
          "longitude": 118.786341
        },
        {
          "latitude": 32.04154,
          "longitude": 118.786765
        },
        {
          "latitude": 32.041518,
          "longitude": 118.787038
        },
        {
          "latitude": 32.041513,
          "longitude": 118.787103
        },
        {
          "latitude": 32.041448,
          "longitude": 118.787961
        },
        {
          "latitude": 32.041438,
          "longitude": 118.788084
        },
        {
          "latitude": 32.041368,
          "longitude": 118.789361
        },
        {
          "latitude": 32.041314,
          "longitude": 118.78993
        },
        {
          "latitude": 32.041271,
          "longitude": 118.790606
        },
        {
          "latitude": 32.041218,
          "longitude": 118.791383
        },
        {
          "latitude": 32.041153,
          "longitude": 118.79236
        },
        {
          "latitude": 32.04111,
          "longitude": 118.793159
        },
        {
          "latitude": 32.041008,
          "longitude": 118.794586
        },
        {
          "latitude": 32.040992,
          "longitude": 118.794822
        },
        {
          "latitude": 32.040955,
          "longitude": 118.795337
        },
        {
          "latitude": 32.040939,
          "longitude": 118.795509
        },
        {
          "latitude": 32.040928,
          "longitude": 118.795691
        },
        {
          "latitude": 32.040906,
          "longitude": 118.795927
        },
        {
          "latitude": 32.04089,
          "longitude": 118.796136
        },
        {
          "latitude": 32.040735,
          "longitude": 118.798105
        },
        {
          "latitude": 32.040655,
          "longitude": 118.799103
        },
        {
          "latitude": 32.040649,
          "longitude": 118.799189
        },
        {
          "latitude": 32.040579,
          "longitude": 118.800594
        },
        {
          "latitude": 32.040558,
          "longitude": 118.800916
        },
        {
          "latitude": 32.040547,
          "longitude": 118.801034
        },
        {
          "latitude": 32.040526,
          "longitude": 118.801383
        },
        {
          "latitude": 32.040499,
          "longitude": 118.801678
        },
        {
          "latitude": 32.040418,
          "longitude": 118.802788
        },
        {
          "latitude": 32.040306,
          "longitude": 118.804408
        },
        {
          "latitude": 32.040268,
          "longitude": 118.804703
        },
        {
          "latitude": 32.040198,
          "longitude": 118.805943
        },
        {
          "latitude": 32.040182,
          "longitude": 118.806152
        },
        {
          "latitude": 32.040156,
          "longitude": 118.806484
        },
        {
          "latitude": 32.040096,
          "longitude": 118.807348
        },
        {
          "latitude": 32.040027,
          "longitude": 118.808217
        },
        {
          "latitude": 32.039989,
          "longitude": 118.808721
        },
        {
          "latitude": 32.039941,
          "longitude": 118.809445
        },
        {
          "latitude": 32.039855,
          "longitude": 118.810341
        },
        {
          "latitude": 32.039796,
          "longitude": 118.81032
        },
        {
          "latitude": 32.03927,
          "longitude": 118.810282
        },
        {
          "latitude": 32.038766,
          "longitude": 118.810271
        },
        {
          "latitude": 32.038595,
          "longitude": 118.810271
        },
        {
          "latitude": 32.038262,
          "longitude": 118.810277
        },
        {
          "latitude": 32.038256,
          "longitude": 118.810373
        },
        {
          "latitude": 32.038595,
          "longitude": 118.810368
        },
        {
          "latitude": 32.038997,
          "longitude": 118.81039
        },
        {
          "latitude": 32.039785,
          "longitude": 118.810459
        },
        {
          "latitude": 32.039936,
          "longitude": 118.810368
        },
        {
          "latitude": 32.039936,
          "longitude": 118.810325
        },
        {
          "latitude": 32.040005,
          "longitude": 118.809365
        },
        {
          "latitude": 32.040054,
          "longitude": 118.808727
        },
        {
          "latitude": 32.040134,
          "longitude": 118.807654
        },
        {
          "latitude": 32.040156,
          "longitude": 118.807359
        },
        {
          "latitude": 32.040171,
          "longitude": 118.80716
        },
        {
          "latitude": 32.040252,
          "longitude": 118.806152
        },
        {
          "latitude": 32.040271,
          "longitude": 118.805938
        }
      ]
    },
    {
      "id": 4,
      "name": "古平岗→汉中门",
      "start": "古平岗站",
      "end": "汉中门站",
      "points": [
        {
          "latitude": 32.071279,
          "longitude": 118.757972
        },
        {
          "latitude": 32.071237,
          "longitude": 118.75748
        },
        {
          "latitude": 32.07106,
          "longitude": 118.755968
        },
        {
          "latitude": 32.071135,
          "longitude": 118.755656
        },
        {
          "latitude": 32.071189,
          "longitude": 118.755533
        },
        {
          "latitude": 32.071237,
          "longitude": 118.755463
        },
        {
          "latitude": 32.071317,
          "longitude": 118.755383
        },
        {
          "latitude": 32.071419,
          "longitude": 118.755313
        },
        {
          "latitude": 32.071591,
          "longitude": 118.75526
        },
        {
          "latitude": 32.071779,
          "longitude": 118.75527
        },
        {
          "latitude": 32.071908,
          "longitude": 118.755318
        },
        {
          "latitude": 32.072047,
          "longitude": 118.75542
        },
        {
          "latitude": 32.072143,
          "longitude": 118.755565
        },
        {
          "latitude": 32.072181,
          "longitude": 118.755678
        },
        {
          "latitude": 32.072192,
          "longitude": 118.755775
        },
        {
          "latitude": 32.072186,
          "longitude": 118.755919
        },
        {
          "latitude": 32.072095,
          "longitude": 118.756311
        },
        {
          "latitude": 32.072079,
          "longitude": 118.756402
        },
        {
          "latitude": 32.071763,
          "longitude": 118.756815
        },
        {
          "latitude": 32.071586,
          "longitude": 118.756981
        },
        {
          "latitude": 32.071435,
          "longitude": 118.757094
        },
        {
          "latitude": 32.071242,
          "longitude": 118.757212
        },
        {
          "latitude": 32.07106,
          "longitude": 118.757303
        },
        {
          "latitude": 32.070867,
          "longitude": 118.757378
        },
        {
          "latitude": 32.070663,
          "longitude": 118.757427
        },
        {
          "latitude": 32.070438,
          "longitude": 118.757459
        },
        {
          "latitude": 32.070175,
          "longitude": 118.757475
        },
        {
          "latitude": 32.069858,
          "longitude": 118.75747
        },
        {
          "latitude": 32.069391,
          "longitude": 118.757438
        },
        {
          "latitude": 32.069091,
          "longitude": 118.757395
        },
        {
          "latitude": 32.068936,
          "longitude": 118.757373
        },
        {
          "latitude": 32.068598,
          "longitude": 118.757303
        },
        {
          "latitude": 32.068265,
          "longitude": 118.757207
        },
        {
          "latitude": 32.066377,
          "longitude": 118.756541
        },
        {
          "latitude": 32.065931,
          "longitude": 118.756408
        },
        {
          "latitude": 32.065889,
          "longitude": 118.756391
        },
        {
          "latitude": 32.065851,
          "longitude": 118.756375
        },
        {
          "latitude": 32.065636,
          "longitude": 118.75629
        },
        {
          "latitude": 32.065433,
          "longitude": 118.756209
        },
        {
          "latitude": 32.065014,
          "longitude": 118.756091
        },
        {
          "latitude": 32.064215,
          "longitude": 118.755919
        },
        {
          "latitude": 32.063534,
          "longitude": 118.75586
        },
        {
          "latitude": 32.062123,
          "longitude": 118.755785
        },
        {
          "latitude": 32.061323,
          "longitude": 118.755748
        },
        {
          "latitude": 32.060401,
          "longitude": 118.755753
        },
        {
          "latitude": 32.060047,
          "longitude": 118.755758
        },
        {
          "latitude": 32.059403,
          "longitude": 118.755801
        },
        {
          "latitude": 32.058105,
          "longitude": 118.755898
        },
        {
          "latitude": 32.05722,
          "longitude": 118.755951
        },
        {
          "latitude": 32.056469,
          "longitude": 118.756064
        },
        {
          "latitude": 32.055905,
          "longitude": 118.75615
        },
        {
          "latitude": 32.055294,
          "longitude": 118.756273
        },
        {
          "latitude": 32.054993,
          "longitude": 118.756332
        },
        {
          "latitude": 32.054902,
          "longitude": 118.756348
        },
        {
          "latitude": 32.054833,
          "longitude": 118.756359
        },
        {
          "latitude": 32.054773,
          "longitude": 118.75637
        },
        {
          "latitude": 32.054398,
          "longitude": 118.756445
        },
        {
          "latitude": 32.05369,
          "longitude": 118.756574
        },
        {
          "latitude": 32.053524,
          "longitude": 118.756606
        },
        {
          "latitude": 32.053298,
          "longitude": 118.756649
        },
        {
          "latitude": 32.051946,
          "longitude": 118.756896
        },
        {
          "latitude": 32.051646,
          "longitude": 118.756863
        },
        {
          "latitude": 32.050847,
          "longitude": 118.756987
        },
        {
          "latitude": 32.05067,
          "longitude": 118.757051
        },
        {
          "latitude": 32.050364,
          "longitude": 118.757175
        },
        {
          "latitude": 32.050251,
          "longitude": 118.757223
        },
        {
          "latitude": 32.050053,
          "longitude": 118.75732
        },
        {
          "latitude": 32.049892,
          "longitude": 118.757405
        },
        {
          "latitude": 32.049693,
          "longitude": 118.757539
        },
        {
          "latitude": 32.04957,
          "longitude": 118.757641
        },
        {
          "latitude": 32.04949,
          "longitude": 118.757733
        },
        {
          "latitude": 32.049296,
          "longitude": 118.757963
        },
        {
          "latitude": 32.049109,
          "longitude": 118.758188
        },
        {
          "latitude": 32.048631,
          "longitude": 118.758768
        },
        {
          "latitude": 32.048358,
          "longitude": 118.7591
        },
        {
          "latitude": 32.048046,
          "longitude": 118.759487
        },
        {
          "latitude": 32.048004,
          "longitude": 118.759535
        },
        {
          "latitude": 32.047612,
          "longitude": 118.759991
        },
        {
          "latitude": 32.047548,
          "longitude": 118.760066
        },
        {
          "latitude": 32.04743,
          "longitude": 118.760205
        },
        {
          "latitude": 32.047312,
          "longitude": 118.76034
        },
        {
          "latitude": 32.047118,
          "longitude": 118.76057
        },
        {
          "latitude": 32.04707,
          "longitude": 118.760629
        },
        {
          "latitude": 32.046823,
          "longitude": 118.760914
        },
        {
          "latitude": 32.046679,
          "longitude": 118.761085
        },
        {
          "latitude": 32.046486,
          "longitude": 118.761311
        },
        {
          "latitude": 32.046035,
          "longitude": 118.761836
        },
        {
          "latitude": 32.045713,
          "longitude": 118.762206
        },
        {
          "latitude": 32.045461,
          "longitude": 118.762501
        },
        {
          "latitude": 32.044447,
          "longitude": 118.763676
        },
        {
          "latitude": 32.044291,
          "longitude": 118.763859
        },
        {
          "latitude": 32.044238,
          "longitude": 118.763923
        },
        {
          "latitude": 32.044179,
          "longitude": 118.763987
        },
        {
          "latitude": 32.043605,
          "longitude": 118.764631
        },
        {
          "latitude": 32.04339,
          "longitude": 118.764851
        },
        {
          "latitude": 32.043138,
          "longitude": 118.765087
        },
        {
          "latitude": 32.042816,
          "longitude": 118.765361
        },
        {
          "latitude": 32.042666,
          "longitude": 118.765468
        },
        {
          "latitude": 32.042275,
          "longitude": 118.765709
        },
        {
          "latitude": 32.042221,
          "longitude": 118.765741
        },
        {
          "latitude": 32.042312,
          "longitude": 118.766123
        },
        {
          "latitude": 32.042393,
          "longitude": 118.766273
        },
        {
          "latitude": 32.042537,
          "longitude": 118.76652
        },
        {
          "latitude": 32.042634,
          "longitude": 118.76675
        },
        {
          "latitude": 32.042688,
          "longitude": 118.766873
        },
        {
          "latitude": 32.042779,
          "longitude": 118.767142
        },
        {
          "latitude": 32.042827,
          "longitude": 118.767346
        },
        {
          "latitude": 32.042843,
          "longitude": 118.767528
        },
        {
          "latitude": 32.042843,
          "longitude": 118.767796
        },
        {
          "latitude": 32.042806,
          "longitude": 118.768236
        },
        {
          "latitude": 32.042763,
          "longitude": 118.768939
        },
        {
          "latitude": 32.042763,
          "longitude": 118.768976
        },
        {
          "latitude": 32.042618,
          "longitude": 118.770934
        },
        {
          "latitude": 32.04258,
          "longitude": 118.771637
        },
        {
          "latitude": 32.042666,
          "longitude": 118.771642
        },
        {
          "latitude": 32.042698,
          "longitude": 118.770934
        },
        {
          "latitude": 32.042736,
          "longitude": 118.770323
        },
        {
          "latitude": 32.042822,
          "longitude": 118.76895
        },
        {
          "latitude": 32.042875,
          "longitude": 118.768236
        },
        {
          "latitude": 32.042886,
          "longitude": 118.768145
        },
        {
          "latitude": 32.042913,
          "longitude": 118.767619
        },
        {
          "latitude": 32.042897,
          "longitude": 118.767335
        },
        {
          "latitude": 32.042851,
          "longitude": 118.767115
        }
      ]
    },
    {
      "id": 5,
      "name": "新模范马路→新街口",
      "start": "新模范马路站",
      "end": "新街口站",
      "points": [
        {
          "latitude": 32.079932,
          "longitude": 118.784127
        },
        {
          "latitude": 32.080077,
          "longitude": 118.784131
        },
        {
          "latitude": 32.080491,
          "longitude": 118.784147
        },
        {
          "latitude": 32.080496,
          "longitude": 118.784029
        },
        {
          "latitude": 32.080078,
          "longitude": 118.784029
        },
        {
          "latitude": 32.078865,
          "longitude": 118.784023
        },
        {
          "latitude": 32.078726,
          "longitude": 118.784023
        },
        {
          "latitude": 32.078447,
          "longitude": 118.784034
        },
        {
          "latitude": 32.077696,
          "longitude": 118.784018
        },
        {
          "latitude": 32.077449,
          "longitude": 118.783986
        },
        {
          "latitude": 32.076795,
          "longitude": 118.783986
        },
        {
          "latitude": 32.076092,
          "longitude": 118.784007
        },
        {
          "latitude": 32.075453,
          "longitude": 118.784034
        },
        {
          "latitude": 32.075003,
          "longitude": 118.784034
        },
        {
          "latitude": 32.073796,
          "longitude": 118.784034
        },
        {
          "latitude": 32.072669,
          "longitude": 118.784034
        },
        {
          "latitude": 32.071607,
          "longitude": 118.784018
        },
        {
          "latitude": 32.070845,
          "longitude": 118.784029
        },
        {
          "latitude": 32.070395,
          "longitude": 118.784013
        },
        {
          "latitude": 32.070223,
          "longitude": 118.784018
        },
        {
          "latitude": 32.070137,
          "longitude": 118.784018
        },
        {
          "latitude": 32.069354,
          "longitude": 118.784007
        },
        {
          "latitude": 32.069295,
          "longitude": 118.784002
        },
        {
          "latitude": 32.069091,
          "longitude": 118.784002
        },
        {
          "latitude": 32.06811,
          "longitude": 118.784007
        },
        {
          "latitude": 32.068077,
          "longitude": 118.784013
        },
        {
          "latitude": 32.06738,
          "longitude": 118.784029
        },
        {
          "latitude": 32.066291,
          "longitude": 118.784023
        },
        {
          "latitude": 32.066098,
          "longitude": 118.784023
        },
        {
          "latitude": 32.065931,
          "longitude": 118.784023
        },
        {
          "latitude": 32.065336,
          "longitude": 118.784023
        },
        {
          "latitude": 32.064805,
          "longitude": 118.784013
        },
        {
          "latitude": 32.064778,
          "longitude": 118.784013
        },
        {
          "latitude": 32.063625,
          "longitude": 118.784034
        },
        {
          "latitude": 32.062713,
          "longitude": 118.784018
        },
        {
          "latitude": 32.062471,
          "longitude": 118.784034
        },
        {
          "latitude": 32.062203,
          "longitude": 118.78405
        },
        {
          "latitude": 32.059371,
          "longitude": 118.784072
        },
        {
          "latitude": 32.058105,
          "longitude": 118.784066
        },
        {
          "latitude": 32.055965,
          "longitude": 118.78405
        },
        {
          "latitude": 32.055621,
          "longitude": 118.78405
        },
        {
          "latitude": 32.055036,
          "longitude": 118.78405
        },
        {
          "latitude": 32.054017,
          "longitude": 118.78405
        },
        {
          "latitude": 32.053969,
          "longitude": 118.78405
        },
        {
          "latitude": 32.053271,
          "longitude": 118.78404
        },
        {
          "latitude": 32.052193,
          "longitude": 118.784045
        },
        {
          "latitude": 32.05185,
          "longitude": 118.78404
        },
        {
          "latitude": 32.051608,
          "longitude": 118.784034
        },
        {
          "latitude": 32.051002,
          "longitude": 118.784023
        },
        {
          "latitude": 32.050364,
          "longitude": 118.784013
        },
        {
          "latitude": 32.050219,
          "longitude": 118.784007
        },
        {
          "latitude": 32.049409,
          "longitude": 118.784007
        },
        {
          "latitude": 32.049259,
          "longitude": 118.784007
        },
        {
          "latitude": 32.048454,
          "longitude": 118.784002
        },
        {
          "latitude": 32.04766,
          "longitude": 118.784034
        },
        {
          "latitude": 32.047118,
          "longitude": 118.784034
        },
        {
          "latitude": 32.045895,
          "longitude": 118.78404
        },
        {
          "latitude": 32.045799,
          "longitude": 118.78404
        },
        {
          "latitude": 32.045134,
          "longitude": 118.784029
        },
        {
          "latitude": 32.044023,
          "longitude": 118.784045
        },
        {
          "latitude": 32.043916,
          "longitude": 118.784045
        },
        {
          "latitude": 32.043503,
          "longitude": 118.784045
        },
        {
          "latitude": 32.041813,
          "longitude": 118.784029
        },
        {
          "latitude": 32.041711,
          "longitude": 118.784029
        },
        {
          "latitude": 32.041389,
          "longitude": 118.784013
        },
        {
          "latitude": 32.039903,
          "longitude": 118.784023
        },
        {
          "latitude": 32.039909,
          "longitude": 118.783948
        },
        {
          "latitude": 32.039914,
          "longitude": 118.783788
        },
        {
          "latitude": 32.03993,
          "longitude": 118.783637
        },
        {
          "latitude": 32.039946,
          "longitude": 118.783498
        },
        {
          "latitude": 32.04,
          "longitude": 118.783197
        },
        {
          "latitude": 32.039673,
          "longitude": 118.78302
        },
        {
          "latitude": 32.039544,
          "longitude": 118.782945
        },
        {
          "latitude": 32.039496,
          "longitude": 118.782918
        },
        {
          "latitude": 32.039383,
          "longitude": 118.782849
        },
        {
          "latitude": 32.039104,
          "longitude": 118.782682
        },
        {
          "latitude": 32.038932,
          "longitude": 118.78258
        },
        {
          "latitude": 32.038916,
          "longitude": 118.78257
        },
        {
          "latitude": 32.038713,
          "longitude": 118.782446
        },
        {
          "latitude": 32.038433,
          "longitude": 118.78294
        },
        {
          "latitude": 32.038214,
          "longitude": 118.78338
        },
        {
          "latitude": 32.038106,
          "longitude": 118.783728
        },
        {
          "latitude": 32.038047,
          "longitude": 118.783927
        },
        {
          "latitude": 32.038063,
          "longitude": 118.784158
        },
        {
          "latitude": 32.039179,
          "longitude": 118.784147
        },
        {
          "latitude": 32.039903,
          "longitude": 118.784141
        },
        {
          "latitude": 32.040129,
          "longitude": 118.784141
        },
        {
          "latitude": 32.040322,
          "longitude": 118.784141
        },
        {
          "latitude": 32.041611,
          "longitude": 118.784161
        }
      ]
    },
    {
      "id": 6,
      "name": "新庄→西安门",
      "start": "新庄站",
      "end": "西安门站",
      "points": [
        {
          "latitude": 32.07688,
          "longitude": 118.810535
        },
        {
          "latitude": 32.07687,
          "longitude": 118.810556
        },
        {
          "latitude": 32.076902,
          "longitude": 118.810738
        },
        {
          "latitude": 32.076929,
          "longitude": 118.810931
        },
        {
          "latitude": 32.076612,
          "longitude": 118.811033
        },
        {
          "latitude": 32.076521,
          "longitude": 118.810658
        },
        {
          "latitude": 32.07643,
          "longitude": 118.810277
        },
        {
          "latitude": 32.076403,
          "longitude": 118.810148
        },
        {
          "latitude": 32.076977,
          "longitude": 118.809864
        },
        {
          "latitude": 32.076811,
          "longitude": 118.809488
        },
        {
          "latitude": 32.076156,
          "longitude": 118.809826
        },
        {
          "latitude": 32.075346,
          "longitude": 118.810293
        },
        {
          "latitude": 32.07511,
          "longitude": 118.810422
        },
        {
          "latitude": 32.074863,
          "longitude": 118.810577
        },
        {
          "latitude": 32.073071,
          "longitude": 118.811452
        },
        {
          "latitude": 32.072959,
          "longitude": 118.811613
        },
        {
          "latitude": 32.072492,
          "longitude": 118.811843
        },
        {
          "latitude": 32.072321,
          "longitude": 118.811924
        },
        {
          "latitude": 32.072063,
          "longitude": 118.812042
        },
        {
          "latitude": 32.071736,
          "longitude": 118.812224
        },
        {
          "latitude": 32.071387,
          "longitude": 118.812412
        },
        {
          "latitude": 32.071253,
          "longitude": 118.812482
        },
        {
          "latitude": 32.071028,
          "longitude": 118.81261
        },
        {
          "latitude": 32.070486,
          "longitude": 118.812922
        },
        {
          "latitude": 32.069799,
          "longitude": 118.813281
        },
        {
          "latitude": 32.069751,
          "longitude": 118.813308
        },
        {
          "latitude": 32.069091,
          "longitude": 118.813651
        },
        {
          "latitude": 32.068775,
          "longitude": 118.813818
        },
        {
          "latitude": 32.06849,
          "longitude": 118.813973
        },
        {
          "latitude": 32.067857,
          "longitude": 118.8143
        },
        {
          "latitude": 32.066843,
          "longitude": 118.814831
        },
        {
          "latitude": 32.066151,
          "longitude": 118.81518
        },
        {
          "latitude": 32.065835,
          "longitude": 118.815346
        },
        {
          "latitude": 32.065293,
          "longitude": 118.815733
        },
        {
          "latitude": 32.064784,
          "longitude": 118.816296
        },
        {
          "latitude": 32.064548,
          "longitude": 118.816618
        },
        {
          "latitude": 32.063957,
          "longitude": 118.817267
        },
        {
          "latitude": 32.063201,
          "longitude": 118.818093
        },
        {
          "latitude": 32.06296,
          "longitude": 118.818329
        },
        {
          "latitude": 32.06252,
          "longitude": 118.818683
        },
        {
          "latitude": 32.062117,
          "longitude": 118.818962
        },
        {
          "latitude": 32.061833,
          "longitude": 118.819123
        },
        {
          "latitude": 32.061501,
          "longitude": 118.819284
        },
        {
          "latitude": 32.060841,
          "longitude": 118.819536
        },
        {
          "latitude": 32.060288,
          "longitude": 118.81967
        },
        {
          "latitude": 32.059977,
          "longitude": 118.819702
        },
        {
          "latitude": 32.059645,
          "longitude": 118.819708
        },
        {
          "latitude": 32.058995,
          "longitude": 118.819659
        },
        {
          "latitude": 32.058105,
          "longitude": 118.819611
        },
        {
          "latitude": 32.054849,
          "longitude": 118.819434
        },
        {
          "latitude": 32.054521,
          "longitude": 118.819418
        },
        {
          "latitude": 32.053888,
          "longitude": 118.819402
        },
        {
          "latitude": 32.053545,
          "longitude": 118.819423
        },
        {
          "latitude": 32.052333,
          "longitude": 118.819573
        },
        {
          "latitude": 32.051786,
          "longitude": 118.81952
        },
        {
          "latitude": 32.051517,
          "longitude": 118.819498
        },
        {
          "latitude": 32.051271,
          "longitude": 118.819477
        },
        {
          "latitude": 32.05074,
          "longitude": 118.819418
        },
        {
          "latitude": 32.050241,
          "longitude": 118.819364
        },
        {
          "latitude": 32.04993,
          "longitude": 118.819327
        },
        {
          "latitude": 32.049591,
          "longitude": 118.819305
        },
        {
          "latitude": 32.049291,
          "longitude": 118.819273
        },
        {
          "latitude": 32.049044,
          "longitude": 118.819236
        },
        {
          "latitude": 32.048755,
          "longitude": 118.819176
        },
        {
          "latitude": 32.048578,
          "longitude": 118.819139
        },
        {
          "latitude": 32.048385,
          "longitude": 118.819096
        },
        {
          "latitude": 32.048014,
          "longitude": 118.819021
        },
        {
          "latitude": 32.047751,
          "longitude": 118.818967
        },
        {
          "latitude": 32.047596,
          "longitude": 118.818935
        },
        {
          "latitude": 32.047542,
          "longitude": 118.81893
        },
        {
          "latitude": 32.047242,
          "longitude": 118.818849
        },
        {
          "latitude": 32.047118,
          "longitude": 118.818801
        },
        {
          "latitude": 32.046861,
          "longitude": 118.818694
        },
        {
          "latitude": 32.04662,
          "longitude": 118.818619
        },
        {
          "latitude": 32.046175,
          "longitude": 118.818533
        },
        {
          "latitude": 32.04537,
          "longitude": 118.81835
        },
        {
          "latitude": 32.045257,
          "longitude": 118.818329
        },
        {
          "latitude": 32.044147,
          "longitude": 118.818211
        },
        {
          "latitude": 32.043771,
          "longitude": 118.818157
        },
        {
          "latitude": 32.043658,
          "longitude": 118.818109
        },
        {
          "latitude": 32.043594,
          "longitude": 118.818034
        },
        {
          "latitude": 32.043519,
          "longitude": 118.817905
        },
        {
          "latitude": 32.043406,
          "longitude": 118.817691
        },
        {
          "latitude": 32.043326,
          "longitude": 118.8176
        },
        {
          "latitude": 32.043235,
          "longitude": 118.817519
        },
        {
          "latitude": 32.043138,
          "longitude": 118.81746
        },
        {
          "latitude": 32.043041,
          "longitude": 118.817422
        },
        {
          "latitude": 32.042768,
          "longitude": 118.81739
        },
        {
          "latitude": 32.041974,
          "longitude": 118.817294
        },
        {
          "latitude": 32.040912,
          "longitude": 118.817176
        },
        {
          "latitude": 32.040402,
          "longitude": 118.817133
        },
        {
          "latitude": 32.039565,
          "longitude": 118.817031
        },
        {
          "latitude": 32.039463,
          "longitude": 118.817015
        },
        {
          "latitude": 32.039523,
          "longitude": 118.816103
        },
        {
          "latitude": 32.039549,
          "longitude": 118.815733
        },
        {
          "latitude": 32.03956,
          "longitude": 118.815593
        },
        {
          "latitude": 32.039603,
          "longitude": 118.814976
        },
        {
          "latitude": 32.039673,
          "longitude": 118.813989
        },
        {
          "latitude": 32.039775,
          "longitude": 118.81253
        },
        {
          "latitude": 32.039844,
          "longitude": 118.81164
        },
        {
          "latitude": 32.039898,
          "longitude": 118.810744
        },
        {
          "latitude": 32.039925,
          "longitude": 118.810475
        },
        {
          "latitude": 32.039936,
          "longitude": 118.810368
        },
        {
          "latitude": 32.039936,
          "longitude": 118.810325
        },
        {
          "latitude": 32.040005,
          "longitude": 118.809365
        },
        {
          "latitude": 32.040054,
          "longitude": 118.808727
        },
        {
          "latitude": 32.040134,
          "longitude": 118.807654
        },
        {
          "latitude": 32.040156,
          "longitude": 118.807359
        },
        {
          "latitude": 32.040171,
          "longitude": 118.80716
        },
        {
          "latitude": 32.040252,
          "longitude": 118.806152
        },
        {
          "latitude": 32.040271,
          "longitude": 118.805938
        }
      ]
    }
  ]
}